pygame_render/__init__.py
pygame_render/engine.py
pygame_render/font_atlas.py
pygame_render/fragment_draw.glsl
pygame_render/fragment_text.glsl
pygame_render/fragment_tone.glsl
pygame_render/layer.py
pygame_render/shader.py
pygame_render/util.py
pygame_render/vertex.glsl
pygame_render-1.4.2.dist-info/licenses/LICENSE
pygame_render-1.4.2.dist-info/METADATA
pygame_render-1.4.2.dist-info/WHEEL
pygame_render-1.4.2.dist-info/top_level.txt
pygame_render-1.4.2.dist-info/RECORD
