Metadata-Version: 2.4
Name: pygame-render
Version: 1.4.2
Summary: Fast 2D render engine for Pygame.
Author: Markel Zubia
License: MIT License
Project-URL: Homepage, https://github.com/MarkelZ/pygame-render
Project-URL: Documentation, https://github.com/MarkelZ/pygame-render/wiki
Project-URL: Bug Reports, https://github.com/MarkelZ/pygame-render/issues
Keywords: pygame,render,shader,shaders,pygame-ce,2D
Classifier: License :: OSI Approved :: MIT License
Classifier: Programming Language :: Python
Classifier: Programming Language :: Python :: 3
Requires-Python: >=3.10
License-File: LICENSE
Requires-Dist: numpy>=1.22.0
Requires-Dist: moderngl>=5.8.2
Requires-Dist: PyOpenGL>=3.1.6
Dynamic: license-file
